space_dl/__init__.py
space_dl/__main__.py
space_dl/twitter_space.py
space_dl-0.1.0.dist-info/LICENSE
space_dl-0.1.0.dist-info/METADATA
space_dl-0.1.0.dist-info/WHEEL
space_dl-0.1.0.dist-info/top_level.txt
space_dl-0.1.0.dist-info/RECORD
