Metadata-Version: 2.1
Name: space-dl
Version: 0.1.0
Summary: Download Twitter Space
Home-page: https://github.com/RYNEQ/space_dl
Author: Ariyan Eghbal
Author-email: ariyan.eghbal@gmail.com
License: UNKNOWN
Platform: UNKNOWN
Classifier: Programming Language :: Python :: 3.8
Classifier: License :: CC0 1.0 Universal (CC0 1.0) Public Domain Dedication
Classifier: Operating System :: OS Independent
License-File: LICENSE
